COPYRIGHT
ez_setup.py
setup.py
bin/zapi-cmd.py
bin/zapi-create-snapvault-snapshot-primary.py
bin/zapi-create-snapvault-snapshot-secondary.py
bin/zapi-getfile.py
bin/zapi-putfile.py
bin/zapi-rename-directory.py
bin/zapi-rm-rf.py
lib/NetAppZAPI.egg-info/PKG-INFO
lib/NetAppZAPI.egg-info/SOURCES.txt
lib/NetAppZAPI.egg-info/dependency_links.txt
lib/NetAppZAPI.egg-info/top_level.txt
lib/netappzapi/__init__.py
lib/netappzapi/debug.py
lib/netappzapi/options.py
lib/netappzapi/util.py
lib/netappzapi/zapi.py
lib/netappzapi/zapi_script_options.py