Metadata-Version: 1.0
Name: NetAppZAPI
Version: 0.5.5
Summary: NetApp Zephyr API library for Python
Home-page: http://www.eigenmagic.com/NetAppZAPI
Author: Justin Warren
Author-email: justin@eigenmagic.com
License: MIT
Keywords: NetApp API ZAPI Zephyr storage administration
Platform: UNKNOWN
Classifier: Development Status :: 4 - Beta
Classifier: Environment :: Console
Classifier: Intended Audience :: System Administrators
Classifier: Intended Audience :: Developers
Classifier: Intended Audience :: Information Technology
Classifier: License :: OSI Approved :: MIT License
Classifier: Natural Language :: English
Classifier: Operating System :: POSIX
Classifier: Programming Language :: Python
Classifier: Topic :: System :: Installation/Setup
Classifier: Topic :: System :: Systems Administration
Classifier: Topic :: Utilities
